swap_layer/__init__.py
swap_layer/config.py
swap_layer/exceptions.py
swap_layer/http.py
swap_layer/py.typed
swap_layer/settings.py
swap_layer/billing/__init__.py
swap_layer/billing/adapter.py
swap_layer/billing/admin.py
swap_layer/billing/apps.py
swap_layer/billing/factory.py
swap_layer/billing/models.py
swap_layer/billing/customers/__init__.py
swap_layer/billing/customers/adapter.py
swap_layer/billing/management/__init__.py
swap_layer/billing/management/commands/__init__.py
swap_layer/billing/management/commands/migrate_payment_provider.py
swap_layer/billing/payment_intents/__init__.py
swap_layer/billing/payment_intents/adapter.py
swap_layer/billing/products/__init__.py
swap_layer/billing/products/adapter.py
swap_layer/billing/providers/__init__.py
swap_layer/billing/providers/stripe.py
swap_layer/billing/subscriptions/__init__.py
swap_layer/billing/subscriptions/adapter.py
swap_layer/communications/__init__.py
swap_layer/communications/email/__init__.py
swap_layer/communications/email/adapter.py
swap_layer/communications/email/admin.py
swap_layer/communications/email/apps.py
swap_layer/communications/email/factory.py
swap_layer/communications/email/models.py
swap_layer/communications/email/providers/__init__.py
swap_layer/communications/email/providers/django_email.py
swap_layer/communications/email/providers/smtp.py
swap_layer/communications/sms/__init__.py
swap_layer/communications/sms/adapter.py
swap_layer/communications/sms/admin.py
swap_layer/communications/sms/apps.py
swap_layer/communications/sms/factory.py
swap_layer/communications/sms/models.py
swap_layer/communications/sms/providers/__init__.py
swap_layer/communications/sms/providers/sns.py
swap_layer/communications/sms/providers/twilio_sms.py
swap_layer/identity/platform/__init__.py
swap_layer/identity/platform/adapter.py
swap_layer/identity/platform/admin.py
swap_layer/identity/platform/apps.py
swap_layer/identity/platform/factory.py
swap_layer/identity/platform/models.py
swaplayer-0.2.6.dist-info/METADATA
swaplayer-0.2.6.dist-info/WHEEL
swaplayer-0.2.6.dist-info/entry_points.txt
swaplayer-0.2.6.dist-info/licenses/LICENSE
swaplayer-0.2.6.dist-info/RECORD
