Metadata-Version: 2.4
Name: SwapLayer
Version: 0.2.6
Summary: Swap providers with zero vendor lock-in. For Django SaaS.
Project-URL: Homepage, https://github.com/Tunet-xyz/swap_layer
Project-URL: Documentation, https://github.com/Tunet-xyz/swap_layer/blob/main/docs/README.md
Project-URL: Repository, https://github.com/Tunet-xyz/swap_layer
Project-URL: Issues, https://github.com/Tunet-xyz/swap_layer/issues
Project-URL: Changelog, https://github.com/Tunet-xyz/swap_layer/blob/main/CHANGELOG.md
Author-email: Alex C <alex@coded.uk>
License-Expression: MIT
License-File: LICENSE
Keywords: anti-vendor-lock-in,aws,django,infrastructure,providers,saas,stripe,twilio
Classifier: Framework :: Django
Classifier: Framework :: Django :: 4.2
Classifier: Framework :: Django :: 5.0
Classifier: Intended Audience :: Developers
Classifier: License :: OSI Approved :: MIT License
Classifier: Programming Language :: Python :: 3
Classifier: Programming Language :: Python :: 3.10
Classifier: Programming Language :: Python :: 3.11
Classifier: Programming Language :: Python :: 3.12
Classifier: Topic :: Software Development :: Libraries :: Python Modules
Requires-Python: >=3.10
Requires-Dist: django>=4.2
Requires-Dist: pydantic>=2.0.0
Requires-Dist: requests>=2.28.0
Requires-Dist: tenacity>=8.0.0
Provides-Extra: all
Requires-Dist: authlib>=1.3.0; extra == 'all'
Requires-Dist: boto3>=1.26.0; extra == 'all'
Requires-Dist: django-anymail>=10.0; extra == 'all'
Requires-Dist: django-storages[azure,s3]>=1.13; extra == 'all'
Requires-Dist: mcp>=0.9.0; extra == 'all'
Requires-Dist: stripe>=5.0.0; extra == 'all'
Requires-Dist: tenacity>=8.0.0; extra == 'all'
Requires-Dist: twilio>=8.0.0; extra == 'all'
Requires-Dist: workos>=1.0.0; extra == 'all'
Provides-Extra: aws
Requires-Dist: boto3>=1.26.0; extra == 'aws'
Requires-Dist: django-storages[s3]>=1.13; extra == 'aws'
Provides-Extra: azure
Requires-Dist: azure-storage-blob>=12.0.0; extra == 'azure'
Requires-Dist: django-storages[azure]>=1.13; extra == 'azure'
Provides-Extra: dev
Requires-Dist: django-stubs>=4.2.0; extra == 'dev'
Requires-Dist: mypy>=1.0.0; extra == 'dev'
Requires-Dist: pytest-asyncio>=0.21.0; extra == 'dev'
Requires-Dist: pytest-cov>=4.0.0; extra == 'dev'
Requires-Dist: pytest>=7.0.0; extra == 'dev'
Requires-Dist: ruff>=0.1.0; extra == 'dev'
Requires-Dist: types-requests>=2.31.0; extra == 'dev'
Provides-Extra: email
Requires-Dist: django-anymail>=10.0; extra == 'email'
Provides-Extra: identity
Requires-Dist: authlib>=1.3.0; extra == 'identity'
Requires-Dist: workos>=1.0.0; extra == 'identity'
Provides-Extra: mcp
Requires-Dist: mcp>=0.9.0; extra == 'mcp'
Provides-Extra: sms
Requires-Dist: twilio>=8.0.0; extra == 'sms'
Provides-Extra: stripe
Requires-Dist: stripe>=5.0.0; extra == 'stripe'
